irker_handler.py
irker_handler-0.0.1.dist-info/METADATA
irker_handler-0.0.1.dist-info/WHEEL
irker_handler-0.0.1.dist-info/top_level.txt
irker_handler-0.0.1.dist-info/RECORD
